happypig/VERSION.txt
happypig/__init__.py
happypig/saying.py
happypig/commands/__init__.py
happypig/commands/main.py
happypig/commands/random_main.py
happypig/data/animals.csv
happypig-0.1.0.dist-info/METADATA
happypig-0.1.0.dist-info/WHEEL
happypig-0.1.0.dist-info/entry_points.txt
happypig-0.1.0.dist-info/top_level.txt
happypig-0.1.0.dist-info/RECORD
